<?xml version="1.0" encoding="UTF-8"?>
<launch4jConfig>
  <dontWrapJar>false</dontWrapJar>
  <headerType>gui</headerType>
  <jar>C:\Users\newu2012\IdeaProjects\ServiceDesk-in-work\serviceDesk_client\target\serviceDesk_client-0.1.0-SNAPSHOT.jar</jar>
  <outfile>C:\Users\newu2012\IdeaProjects\ServiceDesk-in-work\serviceDesk_client\target\serviceDesk_client-0.1.0-SNAPSHOT.exe</outfile>
  <errTitle></errTitle>
  <cmdLine></cmdLine>
  <chdir>.</chdir>
  <priority>normal</priority>
  <downloadUrl>http://java.com/download</downloadUrl>
  <supportUrl></supportUrl>
  <stayAlive>false</stayAlive>
  <restartOnCrash>false</restartOnCrash>
  <manifest></manifest>
  <icon></icon>
  <jre>
    <path>C:\Users\newu2012\.jdks\corretto-11.0.10</path>
    <bundledJre64Bit>false</bundledJre64Bit>
    <bundledJreAsFallback>true</bundledJreAsFallback>
    <minVersion>55</minVersion>
    <maxVersion></maxVersion>
    <jdkPreference>preferJre</jdkPreference>
    <runtimeBits>64/32</runtimeBits>
  </jre>
</launch4jConfig>